{"followLerp":0.06,"defaultCamZoom":0.7,"sprites":[{"pos":[-1184,-917],"src":"stages/discord server/Discord","shader":null,"beatTween":{"ease":"linear","x":0,"y":0},"alpha":1,"scrollFactor":[1,1],"antialiasing":false,"name":"Discord","animation":null,"type":"Bitmap","scale":1.8},{"pos":[272,111.5],"src":"","shader":"","beatTween":null,"alpha":1,"scrollFactor":[1,1],"antialiasing":true,"name":"Girlfriend","animation":null,"type":"GF","scale":1},{"pos":[-122,554],"src":"","shader":"","beatTween":{"x":0,"y":0,"ease":"linear"},"alpha":1,"scrollFactor":[1,1],"antialiasing":true,"name":"Dad","animation":null,"type":"Dad","scale":1},{"pos":[897,58],"src":"","shader":"","beatTween":{"x":0,"y":0,"ease":"linear"},"alpha":1,"scrollFactor":[1,1],"antialiasing":true,"name":"Boyfriend","animation":null,"type":"BF","scale":1}],"gfOffset":[-128,-18.5],"dadOffset":[-232,-26],"bfOffset":[127,-42]}